LICENSE
MANIFEST.in
README.md
pyproject.toml
requirements.txt
setup.py
spec.md
data_processing_utils/__init__.py
data_processing_utils/core.py
data_processing_utils.egg-info/PKG-INFO
data_processing_utils.egg-info/SOURCES.txt
data_processing_utils.egg-info/dependency_links.txt
data_processing_utils.egg-info/top_level.txt